{
  "gitSyncId": "6381f6413e748351b7e698c0_6533f067d36d19549787cbbe",
  "id": "Liabilities_Page_LiabilitiesUtils.myFun1",
  "pluginId": "js-plugin",
  "pluginType": "JS",
  "unpublishedAction": {
    "actionConfiguration": {
      "encodeParamsToggle": true,
      "jsArguments": [],
      "paginationType": "NONE",
      "timeoutInMillisecond": 10000
    },
    "clientSideExecution": true,
    "collectionId": "Liabilities_Page_LiabilitiesUtils",
    "confirmBeforeExecute": false,
    "datasource": {
      "isAutoGenerated": false,
      "name": "UNUSED_DATASOURCE",
      "pluginId": "js-plugin"
    },
    "dynamicBindingPathList": [
      {
        "key": "body"
      }
    ],
    "fullyQualifiedName": "LiabilitiesUtils.myFun1",
    "name": "myFun1",
    "pageId": "Liabilities_Page",
    "runBehaviour": "MANUAL",
    "userSetOnLoad": false
  }
}