{
  "alignment": "center",
  "animateLoading": true,
  "borderRadius": "{{appsmith.theme.borderRadius.appBorderRadius}}",
  "bottomRow": 75.43906250000002,
  "displayName": "Text",
  "dynamicBindingPathList": [
    {
      "key": "truncateButtonColor"
    },
    {
      "key": "fontFamily"
    },
    {
      "key": "borderRadius"
    }
  ],
  "dynamicHeight": "AUTO_HEIGHT",
  "dynamicTriggerPathList": [],
  "flexVerticalAlignment": "end",
  "fontFamily": "{{appsmith.theme.fontFamily.appFont}}",
  "fontSize": "0.875rem",
  "fontStyle": "",
  "hideCard": false,
  "iconSVG": "/static/media/icon.97c59b523e6f70ba6f40a10fc2c7c5b5.svg",
  "isDeprecated": false,
  "isLoading": false,
  "isVisible": true,
  "key": "gidjpgxlhl",
  "leftColumn": 0,
  "maxDynamicHeight": 9000,
  "minDynamicHeight": 4,
  "minWidth": 450,
  "mobileBottomRow": 177.671875,
  "mobileLeftColumn": 0,
  "mobileRightColumn": 64,
  "mobileTopRow": 151.671875,
  "originalBottomRow": 73,
  "originalTopRow": 63,
  "overflow": "NONE",
  "parentColumnSpace": 17.625,
  "parentId": "l2n9aorh2i",
  "parentRowSpace": 10,
  "renderMode": "CANVAS",
  "responsiveBehavior": "fill",
  "rightColumn": 64,
  "searchTags": [
    "typography",
    "paragraph",
    "label"
  ],
  "shouldTruncate": false,
  "text": "We understand the nature of the data collected and take the necessary steps to secure all your data to the best of our abilities. At all times the data belongs to you and can be deleted by you.\n\nWe will never at any point sell your data to any third party and do not use the data for any other purpose than to fulfill the functions of the platform.",
  "textAlign": "CENTER",
  "textColor": "#2563eb",
  "topRow": 66.23906250000002,
  "truncateButtonColor": "{{appsmith.theme.colors.primaryColor}}",
  "type": "TEXT_WIDGET",
  "version": 1,
  "widgetId": "8102b7ewnr",
  "widgetName": "Text14"
}